cvmtrans/__init__.py
cvmtrans/cvmtrans.py
cvmtrans/cvmtrans_cut_tags.py
cvmtrans/cvmtrans_extract_reads.py
cvmtrans/data_process.sh
cvmtrans/embl_parse.py
cvmtrans/embl_parse_test.py
cvmtrans/gb2fa.py
cvmtrans/parse_bam.py
cvmtrans-0.0.9.dist-info/METADATA
cvmtrans-0.0.9.dist-info/WHEEL
cvmtrans-0.0.9.dist-info/entry_points.txt
cvmtrans-0.0.9.dist-info/top_level.txt
cvmtrans-0.0.9.dist-info/RECORD
