Metadata-Version: 2.1
Name: cvmtrans
Version: 0.0.9
Summary: Transposon data process
Home-page: https://github.com/hbucqp/cvmtrans
Author: Qingpo Cui
Author-email: cqp@cau.edu.cn
License: MIT Licence
Keywords: pip,transposon,transposon sequecing
Platform: any
Classifier: Development Status :: 3 - Alpha
Classifier: Intended Audience :: Developers
Classifier: Topic :: Software Development :: Build Tools
Classifier: License :: OSI Approved :: MIT License
Classifier: Programming Language :: Python :: 3
Classifier: Programming Language :: Python :: 3.8
Classifier: Programming Language :: Python :: 3.9
Classifier: Programming Language :: Python :: 3.10
Classifier: Programming Language :: Python :: 3.11
Requires-Dist: Bio
Requires-Dist: pandas
Requires-Dist: setuptools
Requires-Dist: numpy
Requires-Dist: dnaio
Requires-Dist: pysam
